pvcobra/LICENSE
pvcobra/__init__.py
pvcobra/_cobra.py
pvcobra/_factory.py
pvcobra/_util.py
pvcobra/lib/linux/x86_64/libpv_cobra.so
pvcobra/lib/mac/arm64/libpv_cobra.dylib
pvcobra/lib/mac/x86_64/libpv_cobra.dylib
pvcobra/lib/raspberry-pi/arm11/libpv_cobra.so
pvcobra/lib/raspberry-pi/cortex-a53/libpv_cobra.so
pvcobra/lib/raspberry-pi/cortex-a53-aarch64/libpv_cobra.so
pvcobra/lib/raspberry-pi/cortex-a72/libpv_cobra.so
pvcobra/lib/raspberry-pi/cortex-a72-aarch64/libpv_cobra.so
pvcobra/lib/raspberry-pi/cortex-a76/libpv_cobra.so
pvcobra/lib/raspberry-pi/cortex-a76-aarch64/libpv_cobra.so
pvcobra/lib/windows/amd64/libpv_cobra.dll
pvcobra/lib/windows/amd64/pv_ypu_impl_cuda.dll
pvcobra/lib/windows/arm64/libpv_cobra.dll
pvcobra-3.0.1.dist-info/METADATA
pvcobra-3.0.1.dist-info/WHEEL
pvcobra-3.0.1.dist-info/top_level.txt
pvcobra-3.0.1.dist-info/RECORD
